kachlog/__init__.py
kachlog/_changelog.py
kachlog/_version.py
kachlog/_versioning.py
kachlog/commands.py
kachlog/exceptions.py
kachlog/templates.py
kachlog/utils.py
KaChLog-1.2.1.dist-info/LICENSE
KaChLog-1.2.1.dist-info/METADATA
KaChLog-1.2.1.dist-info/WHEEL
KaChLog-1.2.1.dist-info/entry_points.txt
KaChLog-1.2.1.dist-info/top_level.txt
KaChLog-1.2.1.dist-info/RECORD
